nfsn-ddns/__init__.py
nfsn-ddns/__main__.py
nfsn_ddns/__init__.py
nfsn_ddns/__main__.py
nfsn_ddns/auth.py
nfsn_ddns/config.py
nfsn_ddns/defs.py
nfsn_ddns/engine.py
nfsn_ddns/log.py
nfsn_ddns/myip.py
nfsn_ddns/myip_cmd.py
nfsn_ddns/utils.py
nfsn_ddns/win32.py
nfsn_ddns-0.3.0.dist-info/METADATA
nfsn_ddns-0.3.0.dist-info/WHEEL
nfsn_ddns-0.3.0.dist-info/entry_points.txt
nfsn_ddns-0.3.0.dist-info/licenses/LICENSE
nfsn_ddns-0.3.0.dist-info/RECORD
