Metadata-Version: 2.3
Name: nfsn-ddns
Version: 0.3.0
Summary: NearlyFreeSpeech.net Dynamic DNS Utility
Project-URL: Download, https://pypi.python.org/pypi/nfsn-ddns
Project-URL: Source, https://github.com/jdknight/nfsn-ddns
License-File: LICENSE
Classifier: Development Status :: 4 - Beta
Classifier: Environment :: Console
Classifier: License :: OSI Approved :: BSD License
Classifier: Operating System :: OS Independent
Classifier: Programming Language :: Python
Classifier: Programming Language :: Python :: 3
Classifier: Programming Language :: Python :: 3 :: Only
Classifier: Programming Language :: Python :: 3.9
Classifier: Programming Language :: Python :: 3.10
Classifier: Programming Language :: Python :: 3.11
Classifier: Programming Language :: Python :: 3.12
Classifier: Programming Language :: Python :: 3.13
Classifier: Topic :: Internet :: Name Service (DNS)
Classifier: Topic :: Utilities
Requires-Python: >=3.9
Requires-Dist: pyyaml
Requires-Dist: requests>=2.30.0
